pykubectl/__init__.py
pykubectl/exceptions.py
pykubectl/kubectl.py
pykubectl/objects.py
pykubectl/utils.py
pykubectl/yaml_utils.py
PyKubeCtl-1.0.1.dist-info/LICENSE
PyKubeCtl-1.0.1.dist-info/METADATA
PyKubeCtl-1.0.1.dist-info/WHEEL
PyKubeCtl-1.0.1.dist-info/top_level.txt
PyKubeCtl-1.0.1.dist-info/RECORD
