Metadata-Version: 2.1
Name: PyKubeCtl
Version: 1.0.1
Summary: A python bridge to kubectl
Home-page: https://github.com/4Catalyzer/pykubectl
Author: Giacomo Tagliabue
Author-email: giacomo@gmail.com
License: MIT
Keywords: kubernetes docker ci cd
Classifier: Development Status :: 3 - Alpha
Classifier: License :: OSI Approved :: MIT License
Classifier: Operating System :: OS Independent
Classifier: Programming Language :: Python
Classifier: Programming Language :: Python :: 3
License-File: LICENSE
Requires-Dist: PyYAML (>=3.11)
